ninetales/__init__.py
ninetales-0.1.0.dist-info/METADATA
ninetales-0.1.0.dist-info/WHEEL
ninetales-0.1.0.dist-info/licenses/LICENSE
ninetales-0.1.0.dist-info/RECORD
