Metadata-Version: 2.1
Name: ninetales
Version: 0.1.0
Summary: A Python library to convert between Python data model paradigms
Author-email: Gorka Eraña <gera@baselifescience.com>
License-File: LICENSE
Requires-Python: >=3.10
